zs_utils/__init__.py
zs_utils/captcha.py
zs_utils/compare_data.py
zs_utils/currency_converter.py
zs_utils/dict_converter.py
zs_utils/exceptions.py
zs_utils/file_io.py
zs_utils/file_utils.py
zs_utils/function_timeout.py
zs_utils/get_file_extension.py
zs_utils/html_utils.py
zs_utils/import_utils.py
zs_utils/inspect_func.py
zs_utils/json_utils.py
zs_utils/permissions.py
zs_utils/s3_storage_backend.py
zs_utils/time_utils.py
zs_utils/transliterate.py
zs_utils/xml_parser.py
zs_utils/api/__init__.py
zs_utils/api/apps.py
zs_utils/api/base_action.py
zs_utils/api/base_api.py
zs_utils/api/constants.py
zs_utils/api/filters.py
zs_utils/api/models.py
zs_utils/api/serializers.py
zs_utils/api/services.py
zs_utils/api/views.py
zs_utils/api/aliexpress/__init__.py
zs_utils/api/aliexpress/base_api.py
zs_utils/api/aliexpress/core/__init__.py
zs_utils/api/aliexpress/core/category.py
zs_utils/api/aliexpress/core/dropshipping.py
zs_utils/api/aliexpress/core/freight_template.py
zs_utils/api/aliexpress/core/logistics.py
zs_utils/api/aliexpress/core/merchant.py
zs_utils/api/aliexpress/core/order.py
zs_utils/api/aliexpress/core/product.py
zs_utils/api/aliexpress/core/service_template.py
zs_utils/api/aliexpress_russia/__init__.py
zs_utils/api/aliexpress_russia/base_api.py
zs_utils/api/aliexpress_russia/core/__init__.py
zs_utils/api/aliexpress_russia/core/category.py
zs_utils/api/aliexpress_russia/core/chat.py
zs_utils/api/aliexpress_russia/core/order.py
zs_utils/api/aliexpress_russia/core/product.py
zs_utils/api/aliexpress_russia/core/shipment.py
zs_utils/api/amazon/__init__.py
zs_utils/api/amazon/base_api.py
zs_utils/api/amazon/core/__init__.py
zs_utils/api/amazon/core/category.py
zs_utils/api/amazon/core/feed.py
zs_utils/api/amazon/core/listing.py
zs_utils/api/amazon/core/order.py
zs_utils/api/amazon/core/report.py
zs_utils/api/amazon/core/seller.py
zs_utils/api/amocrm/__init__.py
zs_utils/api/amocrm/actions.py
zs_utils/api/amocrm/apps.py
zs_utils/api/amocrm/base_action.py
zonesmart_utils-0.8.0.dist-info/METADATA
zonesmart_utils-0.8.0.dist-info/WHEEL
zonesmart_utils-0.8.0.dist-info/top_level.txt
zonesmart_utils-0.8.0.dist-info/RECORD
