Metadata-Version: 2.1
Name: zonesmart-utils
Version: 0.8.0
Summary: UNKNOWN
Home-page: UNKNOWN
Author: Zonesmart
Author-email: e.beliakov@dev.kokoc.com
License: UNKNOWN
Platform: UNKNOWN
Requires-Dist: PyPDF2 (>=2.10.5)
Requires-Dist: ShopifyAPI (>=12.0.0)
Requires-Dist: bs4 (>=0.0.1)
Requires-Dist: celery (>=5)
Requires-Dist: channels (>=3.0.5)
Requires-Dist: django-environ (>=0.4.5)
Requires-Dist: django-extensions (>=3.2.0)
Requires-Dist: django-filter (>=22.1)
Requires-Dist: django-model-utils (>=4.2.0)
Requires-Dist: django-storages[boto3] (>=1.10.1)
Requires-Dist: django (>=4)
Requires-Dist: djangorestframework-simplejwt (>=5.2.0)
Requires-Dist: djangorestframework (>=3.14)
Requires-Dist: drf-nested-routers (==0.91)
Requires-Dist: ebaysdk (>=2.2.0)
Requires-Dist: geoip2 (==4.8.0)
Requires-Dist: html2text (>=2020.1.16)
Requires-Dist: pdfkit (>=1.0.0)
Requires-Dist: polib (==1.2.0)
Requires-Dist: python-magic (>=0.4.27)
Requires-Dist: pytils (>=0.4.1)
Requires-Dist: simplejson (>=3.16.0)
Requires-Dist: yookassa (>=2.3.2)
